canvas_summary/__init__.py
canvas_summary/_frontend.py
canvas_summary/_version.py
canvas_summary/widget.py
canvas_summary/labextension/package.json
canvas_summary/labextension/static/509.2d298ec4aef2575b054c.js
canvas_summary/labextension/static/remoteEntry.5cb7e994214569876c8f.js
canvas_summary/labextension/static/style.js
canvas_summary/labextension/static/third-party-licenses.json
canvas_summary/nbextension/extension.js
canvas_summary/nbextension/index.js
canvas_summary/standalone/widgets/CanvasSummary.js
canvas_summary/standalone/widgets/CanvasSummary.js.map
canvas_summary-3.9.6.data/data/etc/jupyter/nbconfig/notebook.d/canvas_summary.json
canvas_summary-3.9.6.data/data/share/jupyter/labextensions/canvas-summary/install.json
canvas_summary-3.9.6.data/data/share/jupyter/labextensions/canvas-summary/package.json
canvas_summary-3.9.6.data/data/share/jupyter/labextensions/canvas-summary/static/509.2d298ec4aef2575b054c.js
canvas_summary-3.9.6.data/data/share/jupyter/labextensions/canvas-summary/static/remoteEntry.5cb7e994214569876c8f.js
canvas_summary-3.9.6.data/data/share/jupyter/labextensions/canvas-summary/static/style.js
canvas_summary-3.9.6.data/data/share/jupyter/labextensions/canvas-summary/static/third-party-licenses.json
canvas_summary-3.9.6.data/data/share/jupyter/nbextensions/canvas_summary/extension.js
canvas_summary-3.9.6.data/data/share/jupyter/nbextensions/canvas_summary/index.js
canvas_summary-3.9.6.dist-info/METADATA
canvas_summary-3.9.6.dist-info/WHEEL
canvas_summary-3.9.6.dist-info/top_level.txt
canvas_summary-3.9.6.dist-info/RECORD
